{
"skeleton": {
	"hash": "5fhM1VJTOIw",
	"spine": "4.1.17",
	"x": -109.81,
	"y": -53.65,
	"width": 222,
	"height": 105,
	"images": "./images/",
	"audio": ""
},
"bones": [
	{ "name": "root" },
	{ "name": "Ellipse 5 copy", "parent": "root", "x": -0.91, "y": -24.59 },
	{ "name": "Ellipse 4 copy 2", "parent": "root", "x": 35.85, "y": -12.05 },
	{ "name": "Ellipse 6 copy 2", "parent": "root", "x": -37.11, "y": -5.49 },
	{ "name": "Ellipse 7", "parent": "root", "x": 78.32, "y": 0.78 },
	{ "name": "Ellipse 1", "parent": "root", "x": -75.58, "y": -0.36 },
	{ "name": "Ellipse 8", "parent": "root", "x": -27.42, "y": 14.46 },
	{ "name": "Ellipse 3 copy 4", "parent": "root", "x": 19.89, "y": 21.3 },
	{ "name": "Ellipse 3 copy 5", "parent": "root", "x": 50.1, "y": 30.13 }
],
"slots": [
	{ "name": "Ellipse 8", "bone": "Ellipse 8", "attachment": "Ellipse 8" },
	{ "name": "Ellipse 3 copy 4", "bone": "Ellipse 3 copy 4", "attachment": "Ellipse 3 copy 4" },
	{ "name": "Ellipse 1", "bone": "Ellipse 1", "attachment": "Ellipse 1" },
	{ "name": "Ellipse 3 copy 5", "bone": "Ellipse 3 copy 5", "attachment": "Ellipse 3 copy 5" },
	{ "name": "Ellipse 7", "bone": "Ellipse 7", "attachment": "Ellipse 7" },
	{ "name": "Ellipse 1 copy 2", "bone": "Ellipse 1", "attachment": "Ellipse 1 copy 2" },
	{ "name": "Ellipse 8 copy", "bone": "Ellipse 8", "attachment": "Ellipse 8 copy" },
	{ "name": "Ellipse 3 copy 6", "bone": "Ellipse 3 copy 4", "attachment": "Ellipse 3 copy 6" },
	{ "name": "Ellipse 7 copy 2", "bone": "Ellipse 7", "attachment": "Ellipse 7 copy 2" },
	{ "name": "Ellipse 3 copy 7", "bone": "Ellipse 3 copy 5", "attachment": "Ellipse 3 copy 7" },
	{ "name": "Ellipse 4 copy 2", "bone": "Ellipse 4 copy 2", "attachment": "Ellipse 4 copy 2" },
	{ "name": "Ellipse 6 copy 2", "bone": "Ellipse 6 copy 2", "attachment": "Ellipse 6 copy 2" },
	{ "name": "Ellipse 5 copy", "bone": "Ellipse 5 copy", "attachment": "Ellipse 5 copy" }
],
"skins": [
	{
		"name": "default",
		"attachments": {
			"Ellipse 1": {
				"Ellipse 1": { "x": 1.27, "y": 0.21, "width": 71, "height": 71 }
			},
			"Ellipse 1 copy 2": {
				"Ellipse 1 copy 2": { "x": 2.27, "y": -0.79, "width": 69, "height": 69 }
			},
			"Ellipse 3 copy 4": {
				"Ellipse 3 copy 4": { "x": -0.2, "y": 0.55, "width": 55, "height": 53 }
			},
			"Ellipse 3 copy 5": {
				"Ellipse 3 copy 5": { "x": 0.59, "y": -1.28, "width": 39, "height": 39 }
			},
			"Ellipse 3 copy 6": {
				"Ellipse 3 copy 6": { "x": -0.2, "y": -1.45, "width": 53, "height": 51 }
			},
			"Ellipse 3 copy 7": {
				"Ellipse 3 copy 7": { "x": 0.09, "y": -2.28, "width": 36, "height": 37 }
			},
			"Ellipse 4 copy 2": {
				"Ellipse 4 copy 2": { "x": 0.34, "y": -1.6, "width": 72, "height": 72 }
			},
			"Ellipse 5 copy": {
				"Ellipse 5 copy": { "x": 0.1, "y": -1.06, "width": 56, "height": 56 }
			},
			"Ellipse 6 copy 2": {
				"Ellipse 6 copy 2": { "x": 1.8, "y": -0.66, "width": 75, "height": 75 }
			},
			"Ellipse 7": {
				"Ellipse 7": { "x": -1.13, "y": -1.43, "width": 70, "height": 68 }
			},
			"Ellipse 7 copy 2": {
				"Ellipse 7 copy 2": { "x": -2.63, "y": -1.93, "width": 67, "height": 67 }
			},
			"Ellipse 8": {
				"Ellipse 8": { "x": 0.11, "y": -2.61, "width": 79, "height": 79 }
			},
			"Ellipse 8 copy": {
				"Ellipse 8 copy": { "x": 0.11, "y": -3.61, "width": 75, "height": 75 }
			}
		}
	}
],
"animations": {
	"hit": {
		"bones": {
			"Ellipse 1": {
				"translate": [
					{
						"curve": [ 0.083, 0, 0.25, 11.62, 0.083, 0, 0.25, 0 ]
					},
					{
						"time": 0.3333,
						"x": 11.62,
						"curve": [ 0.417, 11.62, 0.583, 0, 0.417, 0, 0.583, 0 ]
					},
					{ "time": 0.6667 }
				],
				"scale": [
					{
						"curve": [ 0.083, 1, 0.25, 0.85, 0.083, 1, 0.25, 0.85 ]
					},
					{
						"time": 0.3333,
						"x": 0.85,
						"y": 0.85,
						"curve": [ 0.417, 0.85, 0.583, 1, 0.417, 0.85, 0.583, 1 ]
					},
					{ "time": 0.6667 }
				]
			},
			"Ellipse 6 copy 2": {
				"translate": [
					{
						"curve": [ 0.083, 0, 0.25, 4.93, 0.083, 0, 0.25, 0 ]
					},
					{
						"time": 0.3333,
						"x": 4.93,
						"curve": [ 0.417, 4.93, 0.583, 0, 0.417, 0, 0.583, 0 ]
					},
					{ "time": 0.6667 }
				],
				"scale": [
					{
						"curve": [ 0.083, 1, 0.25, 0.85, 0.083, 1, 0.25, 0.85 ]
					},
					{
						"time": 0.3333,
						"x": 0.85,
						"y": 0.85,
						"curve": [ 0.417, 0.85, 0.583, 1, 0.417, 0.85, 0.583, 1 ]
					},
					{ "time": 0.6667 }
				]
			},
			"Ellipse 8": {
				"translate": [
					{
						"curve": [ 0.083, 0, 0.25, 5.98, 0.083, 0, 0.25, -0.35 ]
					},
					{
						"time": 0.3333,
						"x": 5.98,
						"y": -0.35,
						"curve": [ 0.417, 5.98, 0.583, 0, 0.417, -0.35, 0.583, 0 ]
					},
					{ "time": 0.6667 }
				],
				"scale": [
					{
						"curve": [ 0.083, 1, 0.25, 0.85, 0.083, 1, 0.25, 0.85 ]
					},
					{
						"time": 0.3333,
						"x": 0.85,
						"y": 0.85,
						"curve": [ 0.417, 0.85, 0.583, 1, 0.417, 0.85, 0.583, 1 ]
					},
					{ "time": 0.6667 }
				]
			},
			"Ellipse 5 copy": {
				"translate": [
					{
						"curve": [ 0.083, 0, 0.25, 0, 0.083, 0, 0.25, 2.82 ]
					},
					{
						"time": 0.3333,
						"y": 2.82,
						"curve": [ 0.417, 0, 0.583, 0, 0.417, 2.82, 0.583, 0 ]
					},
					{ "time": 0.6667 }
				],
				"scale": [
					{
						"curve": [ 0.083, 1, 0.25, 0.85, 0.083, 1, 0.25, 0.85 ]
					},
					{
						"time": 0.3333,
						"x": 0.85,
						"y": 0.85,
						"curve": [ 0.417, 0.85, 0.583, 1, 0.417, 0.85, 0.583, 1 ]
					},
					{ "time": 0.6667 }
				]
			},
			"Ellipse 3 copy 4": {
				"translate": [
					{
						"curve": [ 0.083, 0, 0.25, -3.87, 0.083, 0, 0.25, 0 ]
					},
					{
						"time": 0.3333,
						"x": -3.87,
						"curve": [ 0.417, -3.87, 0.583, 0, 0.417, 0, 0.583, 0 ]
					},
					{ "time": 0.6667 }
				],
				"scale": [
					{
						"curve": [ 0.083, 1, 0.25, 0.85, 0.083, 1, 0.25, 0.85 ]
					},
					{
						"time": 0.3333,
						"x": 0.85,
						"y": 0.85,
						"curve": [ 0.417, 0.85, 0.583, 1, 0.417, 0.85, 0.583, 1 ]
					},
					{ "time": 0.6667 }
				]
			},
			"Ellipse 4 copy 2": {
				"translate": [
					{
						"curve": [ 0.083, 0, 0.25, -3.87, 0.083, 0, 0.25, 0 ]
					},
					{
						"time": 0.3333,
						"x": -3.87,
						"curve": [ 0.417, -3.87, 0.583, 0, 0.417, 0, 0.583, 0 ]
					},
					{ "time": 0.6667 }
				],
				"scale": [
					{
						"curve": [ 0.083, 1, 0.25, 0.85, 0.083, 1, 0.25, 0.85 ]
					},
					{
						"time": 0.3333,
						"x": 0.85,
						"y": 0.85,
						"curve": [ 0.417, 0.85, 0.583, 1, 0.417, 0.85, 0.583, 1 ]
					},
					{ "time": 0.6667 }
				]
			},
			"Ellipse 3 copy 5": {
				"translate": [
					{
						"curve": [ 0.083, 0, 0.25, -5.98, 0.083, 0, 0.25, -4.58 ]
					},
					{
						"time": 0.3333,
						"x": -5.98,
						"y": -4.58,
						"curve": [ 0.417, -5.98, 0.583, 0, 0.417, -4.58, 0.583, 0 ]
					},
					{ "time": 0.6667 }
				],
				"scale": [
					{
						"curve": [ 0.083, 1, 0.25, 0.85, 0.083, 1, 0.25, 0.85 ]
					},
					{
						"time": 0.3333,
						"x": 0.85,
						"y": 0.85,
						"curve": [ 0.417, 0.85, 0.583, 1, 0.417, 0.85, 0.583, 1 ]
					},
					{ "time": 0.6667 }
				]
			},
			"Ellipse 7": {
				"translate": [
					{
						"curve": [ 0.083, 0, 0.25, -12.32, 0.083, 0, 0.25, 0 ]
					},
					{
						"time": 0.3333,
						"x": -12.32,
						"curve": [ 0.417, -12.32, 0.583, 0, 0.417, 0, 0.583, 0 ]
					},
					{ "time": 0.6667 }
				],
				"scale": [
					{
						"curve": [ 0.083, 1, 0.25, 0.85, 0.083, 1, 0.25, 0.85 ]
					},
					{
						"time": 0.3333,
						"x": 0.85,
						"y": 0.85,
						"curve": [ 0.417, 0.85, 0.583, 1, 0.417, 0.85, 0.583, 1 ]
					},
					{ "time": 0.6667 }
				]
			}
		}
	},
	"idle": {
		"bones": {
			"Ellipse 8": {
				"scale": [
					{
						"curve": [ 0.083, 1, 0.25, 0.97, 0.083, 1, 0.25, 0.97 ]
					},
					{
						"time": 0.3333,
						"x": 0.97,
						"y": 0.97,
						"curve": [ 0.417, 0.97, 0.583, 1, 0.417, 0.97, 0.583, 1 ]
					},
					{ "time": 0.6667 }
				]
			},
			"Ellipse 1": {
				"scale": [
					{
						"curve": [ 0.083, 1, 0.25, 0.97, 0.083, 1, 0.25, 0.97 ]
					},
					{
						"time": 0.3333,
						"x": 0.97,
						"y": 0.97,
						"curve": [ 0.417, 0.97, 0.583, 1, 0.417, 0.97, 0.583, 1 ]
					},
					{ "time": 0.6667 }
				]
			},
			"Ellipse 4 copy 2": {
				"scale": [
					{
						"curve": [ 0.083, 1, 0.25, 1.03, 0.083, 1, 0.25, 1.03 ]
					},
					{
						"time": 0.3333,
						"x": 1.03,
						"y": 1.03,
						"curve": [ 0.417, 1.03, 0.583, 1, 0.417, 1.03, 0.583, 1 ]
					},
					{ "time": 0.6667 }
				]
			},
			"Ellipse 7": {
				"scale": [
					{
						"curve": [ 0.083, 1, 0.25, 1.03, 0.083, 1, 0.25, 1.03 ]
					},
					{
						"time": 0.3333,
						"x": 1.03,
						"y": 1.03,
						"curve": [ 0.417, 1.03, 0.583, 1, 0.417, 1.03, 0.583, 1 ]
					},
					{ "time": 0.6667 }
				]
			},
			"Ellipse 3 copy 4": {
				"scale": [
					{
						"curve": [ 0.083, 1, 0.25, 1.03, 0.083, 1, 0.25, 1.03 ]
					},
					{
						"time": 0.3333,
						"x": 1.03,
						"y": 1.03,
						"curve": [ 0.417, 1.03, 0.583, 1, 0.417, 1.03, 0.583, 1 ]
					},
					{ "time": 0.6667 }
				]
			},
			"Ellipse 3 copy 5": {
				"translate": [
					{
						"curve": [ 0.083, 0, 0.25, 0, 0.083, 0, 0.25, -0.35 ]
					},
					{
						"time": 0.3333,
						"y": -0.35,
						"curve": [ 0.417, 0, 0.583, 0, 0.417, -0.35, 0.583, 0 ]
					},
					{ "time": 0.6667 }
				],
				"scale": [
					{
						"curve": [ 0.083, 1, 0.25, 0.97, 0.083, 1, 0.25, 0.97 ]
					},
					{
						"time": 0.3333,
						"x": 0.97,
						"y": 0.97,
						"curve": [ 0.417, 0.97, 0.583, 1, 0.417, 0.97, 0.583, 1 ]
					},
					{ "time": 0.6667 }
				]
			},
			"Ellipse 5 copy": {
				"scale": [
					{
						"curve": [ 0.083, 1, 0.25, 1.03, 0.083, 1, 0.25, 1.03 ]
					},
					{
						"time": 0.3333,
						"x": 1.03,
						"y": 1.03,
						"curve": [ 0.417, 1.03, 0.583, 1, 0.417, 1.03, 0.583, 1 ]
					},
					{ "time": 0.6667 }
				]
			},
			"Ellipse 6 copy 2": {
				"scale": [
					{
						"curve": [ 0.083, 1, 0.25, 0.97, 0.083, 1, 0.25, 0.97 ]
					},
					{
						"time": 0.3333,
						"x": 0.97,
						"y": 0.97,
						"curve": [ 0.417, 0.97, 0.583, 1, 0.417, 0.97, 0.583, 1 ]
					},
					{ "time": 0.6667 }
				]
			}
		}
	},
	"off": {
		"bones": {
			"Ellipse 1": {
				"translate": [
					{
						"curve": [ 0.125, 0, 0.375, 11.26, 0.125, 0, 0.375, -8.8 ]
					},
					{ "time": 0.5, "x": 11.26, "y": -8.8 }
				],
				"scale": [
					{
						"curve": [ 0.167, 1, 0.5, 0, 0.167, 1, 0.5, 0 ]
					},
					{ "time": 0.6667, "x": 0, "y": 0 }
				]
			},
			"Ellipse 8": {
				"translate": [
					{
						"curve": [ 0.083, 0, 0.25, 0, 0.083, 0, 0.25, -7.74 ]
					},
					{ "time": 0.3333, "y": -7.74 }
				],
				"scale": [
					{
						"time": 0.1667,
						"curve": [ 0.333, 1, 0.667, 0, 0.333, 1, 0.667, 0 ]
					},
					{ "time": 0.8333, "x": 0, "y": 0 }
				]
			},
			"Ellipse 3 copy 4": {
				"translate": [
					{
						"time": 0.1667,
						"curve": [ 0.25, 0, 0.417, 0, 0.25, 0, 0.417, -10.56 ]
					},
					{ "time": 0.5, "y": -10.56 }
				],
				"scale": [
					{
						"time": 0.3333,
						"curve": [ 0.417, 1, 0.583, 0, 0.417, 1, 0.583, 0 ]
					},
					{ "time": 0.6667, "x": 0, "y": 0 }
				]
			},
			"Ellipse 3 copy 5": {
				"translate": [
					{
						"time": 0.1667,
						"curve": [ 0.25, 0, 0.417, 0, 0.25, 0, 0.417, -12.32 ]
					},
					{ "time": 0.5, "y": -12.32 }
				],
				"scale": [
					{
						"time": 0.3333,
						"curve": [ 0.417, 1, 0.583, 0, 0.417, 1, 0.583, 0 ]
					},
					{ "time": 0.6667, "x": 0, "y": 0 }
				]
			},
			"Ellipse 7": {
				"translate": [
					{
						"time": 0.1667,
						"curve": [ 0.25, 0, 0.417, 0, 0.25, 0, 0.417, -2.46 ]
					},
					{ "time": 0.5, "y": -2.46 }
				],
				"scale": [
					{
						"time": 0.5,
						"curve": [ 0.583, 1, 0.75, 0, 0.583, 1, 0.75, 0 ]
					},
					{ "time": 0.8333, "x": 0, "y": 0 }
				]
			},
			"Ellipse 6 copy 2": {
				"translate": [
					{
						"curve": [ 0.083, 0, 0.25, 0, 0.083, 0, 0.25, -4.22 ]
					},
					{ "time": 0.3333, "y": -4.22 }
				],
				"scale": [
					{
						"time": 0.3333,
						"curve": [ 0.417, 1, 0.583, 1.05, 0.417, 1, 0.583, 1.05 ]
					},
					{
						"time": 0.6667,
						"x": 1.05,
						"y": 1.05,
						"curve": [ 0.75, 1.05, 0.917, 0, 0.75, 1.05, 0.917, 0 ]
					},
					{ "time": 1, "x": 0, "y": 0 }
				]
			},
			"Ellipse 5 copy": {
				"translate": [
					{
						"curve": [ 0.083, 0, 0.25, 0, 0.083, 0, 0.25, -3.52 ]
					},
					{ "time": 0.3333, "y": -3.52 }
				],
				"scale": [
					{
						"time": 0.3333,
						"curve": [ 0.417, 1, 0.583, 1.05, 0.417, 1, 0.583, 1.05 ]
					},
					{
						"time": 0.6667,
						"x": 1.05,
						"y": 1.05,
						"curve": [ 0.792, 1.05, 1.042, 0, 0.792, 1.05, 1.042, 0 ]
					},
					{ "time": 1.1667, "x": 0, "y": 0 }
				]
			},
			"Ellipse 4 copy 2": {
				"translate": [
					{
						"curve": [ 0.083, 0, 0.25, 0, 0.083, 0, 0.25, -2.11 ]
					},
					{ "time": 0.3333, "y": -2.11 }
				],
				"scale": [
					{
						"time": 0.3333,
						"curve": [ 0.417, 1, 0.583, 1.05, 0.417, 1, 0.583, 1.05 ]
					},
					{
						"time": 0.6667,
						"x": 1.05,
						"y": 1.05,
						"curve": [ 0.833, 1.05, 1.167, 0, 0.833, 1.05, 1.167, 0 ]
					},
					{ "time": 1.3333, "x": 0, "y": 0 }
				]
			}
		}
	},
	"on": {
		"bones": {
			"Ellipse 5 copy": {
				"scale": [
					{ "x": 0, "y": 0, "curve": "stepped" },
					{
						"time": 0.7667,
						"x": 0,
						"y": 0,
						"curve": [ 0.85, 0, 1.017, 1.3, 0.85, 0, 1.017, 1.3 ]
					},
					{
						"time": 1.1,
						"x": 1.3,
						"y": 1.3,
						"curve": [ 1.142, 1.3, 1.225, 1, 1.142, 1.3, 1.225, 1 ]
					},
					{ "time": 1.2667 }
				]
			},
			"Ellipse 4 copy 2": {
				"scale": [
					{ "x": 0, "y": 0, "curve": "stepped" },
					{
						"time": 0.8333,
						"x": 0,
						"y": 0,
						"curve": [ 0.917, 0, 1.083, 1.3, 0.917, 0, 1.083, 1.3 ]
					},
					{
						"time": 1.1667,
						"x": 1.3,
						"y": 1.3,
						"curve": [ 1.208, 1.3, 1.292, 1, 1.208, 1.3, 1.292, 1 ]
					},
					{ "time": 1.3333 }
				]
			},
			"Ellipse 6 copy 2": {
				"scale": [
					{ "x": 0, "y": 0, "curve": "stepped" },
					{
						"time": 0.6667,
						"x": 0,
						"y": 0,
						"curve": [ 0.75, 0, 0.917, 1.2, 0.75, 0, 0.917, 1.2 ]
					},
					{
						"time": 1,
						"x": 1.2,
						"y": 1.2,
						"curve": [ 1.042, 1.2, 1.125, 1, 1.042, 1.2, 1.125, 1 ]
					},
					{ "time": 1.1667 }
				]
			},
			"Ellipse 7": {
				"scale": [
					{ "x": 0, "y": 0, "curve": "stepped" },
					{
						"time": 0.4,
						"x": 0,
						"y": 0,
						"curve": [ 0.483, 0, 0.65, 1.3, 0.483, 0, 0.65, 1.3 ]
					},
					{
						"time": 0.7333,
						"x": 1.3,
						"y": 1.3,
						"curve": [ 0.775, 1.3, 0.858, 1, 0.775, 1.3, 0.858, 1 ]
					},
					{ "time": 0.9 }
				]
			},
			"Ellipse 1": {
				"scale": [
					{
						"x": 0,
						"y": 0,
						"curve": [ 0.083, 0, 0.25, 1.5, 0.083, 0, 0.25, 1.5 ]
					},
					{
						"time": 0.3333,
						"x": 1.5,
						"y": 1.5,
						"curve": [ 0.375, 1.5, 0.458, 1, 0.375, 1.5, 0.458, 1 ]
					},
					{ "time": 0.5 }
				]
			},
			"Ellipse 8": {
				"scale": [
					{ "x": 0, "y": 0, "curve": "stepped" },
					{
						"time": 0.1,
						"x": 0,
						"y": 0,
						"curve": [ 0.183, 0, 0.35, 1.3, 0.183, 0, 0.35, 1.3 ]
					},
					{
						"time": 0.4333,
						"x": 1.3,
						"y": 1.3,
						"curve": [ 0.475, 1.3, 0.558, 1, 0.475, 1.3, 0.558, 1 ]
					},
					{ "time": 0.6 }
				]
			},
			"Ellipse 3 copy 4": {
				"scale": [
					{ "x": 0, "y": 0, "curve": "stepped" },
					{
						"time": 0.2,
						"x": 0,
						"y": 0,
						"curve": [ 0.283, 0, 0.45, 1.5, 0.283, 0, 0.45, 1.5 ]
					},
					{
						"time": 0.5333,
						"x": 1.5,
						"y": 1.5,
						"curve": [ 0.575, 1.5, 0.658, 1, 0.575, 1.5, 0.658, 1 ]
					},
					{ "time": 0.7 }
				]
			},
			"Ellipse 3 copy 5": {
				"scale": [
					{ "x": 0, "y": 0, "curve": "stepped" },
					{
						"time": 0.3,
						"x": 0,
						"y": 0,
						"curve": [ 0.383, 0, 0.55, 1.5, 0.383, 0, 0.55, 1.5 ]
					},
					{
						"time": 0.6333,
						"x": 1.5,
						"y": 1.5,
						"curve": [ 0.675, 1.5, 0.758, 1, 0.675, 1.5, 0.758, 1 ]
					},
					{ "time": 0.8 }
				]
			}
		}
	}
}
}